pageblocks/__init__.py
pageblocks/admin.py
pageblocks/blocks.py
pageblocks/forms.py
pageblocks/models.py
pageblocks/tests.py
pageblocks/utils.py
pageblocks/views.py
pageblocks/migrations/0001_initial.py
pageblocks/migrations/0002_auto_20211012_1854.py
pageblocks/migrations/0003_auto_20211107_1804.py
pageblocks/migrations/0004_image.py
pageblocks/migrations/0005_remove_pageblock_language_pageblock_i18n_data.py
pageblocks/migrations/__init__.py
pageblocks/migrations/__pycache__/0001_initial.cpython-310.pyc
pageblocks/migrations/__pycache__/0001_initial.cpython-39.pyc
pageblocks/migrations/__pycache__/0002_auto_20211012_1854.cpython-310.pyc
pageblocks/migrations/__pycache__/0002_auto_20211012_1854.cpython-39.pyc
pageblocks/migrations/__pycache__/0003_auto_20211107_1751.cpython-39.pyc
pageblocks/migrations/__pycache__/0003_auto_20211107_1804.cpython-310.pyc
pageblocks/migrations/__pycache__/0003_auto_20211107_1804.cpython-39.pyc
pageblocks/migrations/__pycache__/0004_image.cpython-310.pyc
pageblocks/migrations/__pycache__/0004_image.cpython-39.pyc
pageblocks/migrations/__pycache__/0005_remove_pageblock_language_pageblock_i18n_data.cpython-310.pyc
pageblocks/migrations/__pycache__/__init__.cpython-310.pyc
pageblocks/migrations/__pycache__/__init__.cpython-39.pyc
pageblocks/static/admin/pageblocks/css/change_form.css
pageblocks/static/admin/pageblocks/js/change_form.js
pageblocks/templates/admin/pageblocks/block_editor.html
pageblocks/templates/admin/pageblocks/change_form.html
pageblocks/templates/admin/pageblocks/multi_language_input.html
pageblocks/templates/pageblocks/blocks/container.html
pageblocks/templates/pageblocks/blocks/html.html
pageblocks/templates/pageblocks/blocks/image.html
pageblocks/templatetags/__init__.py
pageblocks/templatetags/pageblocks.py
pageblocks/templatetags/__pycache__/__init__.cpython-310.pyc
pageblocks/templatetags/__pycache__/__init__.cpython-39.pyc
pageblocks/templatetags/__pycache__/pageblocks.cpython-310.pyc
django_page_blocks-0.4.1.dist-info/LICENSE
django_page_blocks-0.4.1.dist-info/METADATA
django_page_blocks-0.4.1.dist-info/WHEEL
django_page_blocks-0.4.1.dist-info/top_level.txt
django_page_blocks-0.4.1.dist-info/RECORD
