Metadata-Version: 2.1
Name: django-page-blocks
Version: 0.4.1
Summary: A simple, Wagtail CMS inspired multi language content block engine for Django.  Intended to give slightly more control than regular flatpages.
Home-page: https://github.com/bravasoftware/django-page-blocks
Author: Mark Skelton
Author-email: studio@bravasoftware.com
License: MIT License
Platform: UNKNOWN
Classifier: Environment :: Web Environment
Classifier: Framework :: Django
Classifier: Framework :: Django :: 3.2
Classifier: Framework :: Django :: 4.0
Classifier: Framework :: Django :: 4.1
Classifier: Intended Audience :: Developers
Classifier: License :: OSI Approved :: MIT License
Classifier: Operating System :: OS Independent
Classifier: Programming Language :: Python
Classifier: Programming Language :: Python :: 3.9
Classifier: Programming Language :: Python :: 3.10
Classifier: Topic :: Internet :: WWW/HTTP
Classifier: Topic :: Internet :: WWW/HTTP :: Dynamic Content
License-File: LICENSE
